bohr_library-0.1.1.dist-info/licenses/LICENSE
src/energy.py
src/plot_orbits.py
src/radius.py
src/transition.py
test/test.py
bohr_library-0.1.1.dist-info/METADATA
bohr_library-0.1.1.dist-info/WHEEL
bohr_library-0.1.1.dist-info/top_level.txt
bohr_library-0.1.1.dist-info/RECORD
