Metadata-Version: 2.4
Name: bohr-library
Version: 0.1.1
Summary: Python package to calculate energy levels, orbital radii, and electronic transitions for the Bohr model of hydrogen and hydrogen-like atoms, with educational visualizations.
Author-email: Angie Lorena Pineda Morales <anlopimo580@gmail.com>
License: MIT License
Project-URL: Homepage, https://github.com/angielorenapm/Bohr_Library
Project-URL: Bug Tracker, https://github.com/angielorenapm/Bohr_Library/issues
Project-URL: Documentation, https://github.com/angielorenapm/Bohr_Library/wiki
Keywords: bohr,physics,atomic-model,hydrogen,education
Classifier: Development Status :: 3 - Alpha
Classifier: Intended Audience :: Education
Classifier: Topic :: Scientific/Engineering :: Physics
Classifier: License :: OSI Approved :: MIT License
Classifier: Programming Language :: Python :: 3
Classifier: Operating System :: OS Independent
Requires-Python: >=3.8
License-File: LICENSE
Requires-Dist: numpy>=1.23
Requires-Dist: matplotlib>=3.7
Dynamic: license-file
